{"title": "My view today from Cape Perpetua.", "name": "t3_pi0b7k", "url": "https://i.redd.it/g8c38u8n3kl71.jpg", "selftext": "", "score": 25, "upvote_ratio": 1.0, "permalink": "/r/TheFlyingTree/comments/pi0b7k/my_view_today_from_cape_perpetua/", "id": "pi0b7k", "author": "boringlesbian", "link_flair_text": "Fascinating", "num_comments": 6, "over_18": false, "spoiler": false, "pinned": false, "locked": false, "distinguished": null, "created_utc": 1630791756.0, "comments": [{"author": "BasilDream", "id": "hbm9sqe", "score": 2, "subreddit": "TheFlyingTree", "author_flair": "Acolyte #163 | Classis Veritatus", "submission": "pi0b7k", "stickied": false, "body": "Beautiful!", "is_submitter": false, "distinguished": null, "created_utc": 1630792944.0, "parent_id": "t3_pi0b7k", "replies": []}, {"author": "cocobisoil", "id": "hbmbx1p", "score": 2, "subreddit": "TheFlyingTree", "author_flair": "Seeker #87", "submission": "pi0b7k", "stickied": false, "body": "I could sit there for a while like, stunning.", "is_submitter": false, "distinguished": null, "created_utc": 1630793984.0, "parent_id": "t3_pi0b7k", "replies": []}, {"author": "ItsJustAnAdFor", "id": "hbmy95r", "score": 2, "subreddit": "TheFlyingTree", "author_flair": "Seeker #73", "submission": "pi0b7k", "stickied": false, "body": "\u201cOh lord, make me a bird so I can fly, far far away from here\u2026\n\u2026To Cape Perpetua\u201d", "is_submitter": false, "distinguished": null, "created_utc": 1630805369.0, "parent_id": "t3_pi0b7k", "replies": []}, {"author": "prajnadhyana", "id": "hbnayls", "score": 2, "subreddit": "TheFlyingTree", "author_flair": "Seeker #168", "submission": "pi0b7k", "stickied": false, "body": "Hey, I've been there! Quite a few times. Nice.\n\nDid you go down there to Thor's Well and the Spouting Horn after?", "is_submitter": false, "distinguished": null, "created_utc": 1630812223.0, "parent_id": "t3_pi0b7k", "replies": [{"author": "boringlesbian", "id": "hbomspi", "score": 2, "subreddit": "TheFlyingTree", "author_flair": "Seeker #261 | Consortii Concordus", "submission": "pi0b7k", "stickied": false, "body": "We stopped at Devil\u2019s Churn but didn\u2019t go as far as Thor\u2019s Well. We\u2019ve been there several times over the years though. Some of my favorite parts of the coast.", "is_submitter": true, "distinguished": null, "created_utc": 1630848143.0, "parent_id": "t1_hbnayls", "replies": []}]}, {"author": "prajnadhyana", "id": "hbnccf0", "score": 2, "subreddit": "TheFlyingTree", "author_flair": "Seeker #168", "submission": "pi0b7k", "stickied": false, "body": "Here is the view from waaaaay down there looking up to here. \n\nhttps://i.imgur.com/qCnx7ku.jpg", "is_submitter": false, "distinguished": null, "created_utc": 1630813019.0, "parent_id": "t3_pi0b7k", "replies": []}]}