{"title": "Sorting Hat Hath Spoken!", "name": "t3_p8n3ev", "url": "https://i.redd.it/76npkh5qwni71.png", "selftext": "", "score": 16, "upvote_ratio": 0.75, "permalink": "/r/TheFlyingTree/comments/p8n3ev/sorting_hat_hath_spoken/", "id": "p8n3ev", "author": "FalconRelevant", "link_flair_text": "META", "num_comments": 87, "over_18": false, "spoiler": false, "pinned": false, "locked": false, "distinguished": "moderator", "created_utc": 1629530373.0, "comments": [{"author": "FalconRelevant", "id": "h9rjghf", "score": 1, "subreddit": "TheFlyingTree", "author_flair": "Archon", "submission": "p8n3ev", "stickied": true, "body": "The following have been sorted into Legio Vertus:-\n\n* baalroo\n* Timotioman\n* Eisenthorne \n* zealousideal_mix_629\n* weeb2000\n* Itsjustanadfor\n* The_Ultimate_Fakr\n* Abject_hall7810\n* TrueNinjafrog\n* uptightbean\n* Shadowfires024\n* chocol8cek\n* notdeepee\n* ToastyCaribou84.\n* Sweber145\n* caparisme\n* koboldkiller\n* MelchiorBarbosa\n* qwertyter\n* olkver\n* raedr7n\n* L4sgc\n* Varloust\n\nThe following have been sorted into Consortio Concordia:-\n\n* Riadys\n* developedby\n* here_4_cat_memes\n* Bethcano\n* banana_kiwi\n* Tessapotamus\n* rogue_skywalker\n* Kelyaan\n* Factmysterious \n* Hjemi\n* artsymarcy\n* PlsGiveMeBetterName\n* dnixl\n* ThegreatestHK\n* Wizicist\n* Fri3dNstuff\n* CielTheEarl\n* Low_Kaleidoscope_369\n* Prajnadhyana\n* FiannaTheBard \n* boringlesbian\n* Kweldulf\n* clovepod\n\nThe following have been sorted into Ordo Cognitus:-\n\n* Soulwanderer\n* stachldrat\n* Mr--Elephant\n* gerkletoss\n* TickoTicko-Nii\n* kinasch\n* sarini11\n* EvilCookie4250\n* Cognizant_Psyche\n* SavnetSinn\n* PurpleDevilR\n* iseeverything\n* FnchWzrd314\n* Cynn13\n* The_Holy_Fork\n* bolrnly\n* skopokes44\n* GioRaffe32\n* enhtie \n* IamTJcon\n* Modernzen\n* MatthewofFinance\n\nThe following have been sorted into Classis Veritatus:-\n\n* jmcsquared\n* TheLittlestHibou\n* Summonest\n* ToniMCP109\n* Shig23\n* VenomOUShazard \n* Kranot\n* BasilDream\n* Netzapper\n* Haikouden\n* U_L_Uus\n* BariSaxGod\n* ChillAzDude\n* ravenclaw1138\n* Trzef\n* French-Potatoes\n* alert_watercress4998\n* Chewbaccataco\n* Zabawa13\n* abraculax\n* CemeteryWind213\n* solongfish99", "is_submitter": true, "distinguished": "moderator", "created_utc": 1629530672.0, "parent_id": "t3_p8n3ev", "replies": []}, {"author": "gerkletoss", "id": "h9rpsm3", "score": 6, "subreddit": "TheFlyingTree", "author_flair": "Seeker #291 | Ordo Cognitus", "submission": "p8n3ev", "stickied": false, "body": "Alright, Ordo Cognitus, let's form a plan. I'm not sober at the moment, but establishing comms is step one", "is_submitter": false, "distinguished": null, "created_utc": 1629536205.0, "parent_id": "t3_p8n3ev", "replies": []}, {"author": "Alert_Watercress4998", "id": "h9rr2k4", "score": 5, "subreddit": "TheFlyingTree", "author_flair": "Seeker #34", "submission": "p8n3ev", "stickied": false, "body": "Are the teams going to be shown in our flairs, or is it just going to be for events and such?", "is_submitter": false, "distinguished": null, "created_utc": 1629537353.0, "parent_id": "t3_p8n3ev", "replies": [{"author": "FalconRelevant", "id": "h9rsnai", "score": 6, "subreddit": "TheFlyingTree", "author_flair": "Archon", "submission": "p8n3ev", "stickied": false, "body": "They'll be on your flairs.", "is_submitter": true, "distinguished": null, "created_utc": 1629538763.0, "parent_id": "t1_h9rr2k4", "replies": [{"author": "BrynneRaine", "id": "h9sqa6e", "score": 2, "subreddit": "TheFlyingTree", "author_flair": "Druid #13", "submission": "p8n3ev", "stickied": false, "body": "Testing.  Don\u2019t see myself.  Now that I see the descriptions I would have nominated myself for Veritatus instead.", "is_submitter": false, "distinguished": null, "created_utc": 1629559458.0, "parent_id": "t1_h9rsnai", "replies": [{"author": "horse_loose_hospital", "id": "h9srx3a", "score": 1, "subreddit": "TheFlyingTree", "author_flair": "Seeker #128", "submission": "p8n3ev", "stickied": false, "body": "I'm not there either. Boooourns. I'd def be in ~~Ravenclaw~~ Cognitvs tho lol", "is_submitter": false, "distinguished": null, "created_utc": 1629560200.0, "parent_id": "t1_h9sqa6e", "replies": [{"author": "Hjemi", "id": "h9xiycn", "score": 2, "subreddit": "TheFlyingTree", "author_flair": "Seeker #203 | Consortii Concordus", "submission": "p8n3ev", "stickied": false, "body": "I'm guessing it just takes awhile? I'm not sure if the mods have to manually add it or something, but I'd imagine thst would take awhile.\n\nMine took hours to show up", "is_submitter": false, "distinguished": null, "created_utc": 1629652902.0, "parent_id": "t1_h9srx3a", "replies": [{"author": "TrueNinjafrog", "id": "h9zc6tn", "score": 1, "subreddit": "TheFlyingTree", "author_flair": "Seeker #146 | Legio Virtus", "submission": "p8n3ev", "stickied": false, "body": "Commenting to see if I have mine...\n\nedit: sweet", "is_submitter": false, "distinguished": null, "created_utc": 1629682785.0, "parent_id": "t1_h9xiycn", "replies": []}]}]}]}, {"author": "chewbaccataco", "id": "h9uujkj", "score": 1, "subreddit": "TheFlyingTree", "author_flair": "Seeker #67 | Classis Veritatus", "submission": "p8n3ev", "stickied": false, "body": "Falcon, I took the survey and I am on the list as being sorted, but it is not on my flair. Are you able to help?", "is_submitter": false, "distinguished": null, "created_utc": 1629595173.0, "parent_id": "t1_h9rsnai", "replies": []}]}]}, {"author": "Stand_kicker", "id": "h9rk8sn", "score": 3, "subreddit": "TheFlyingTree", "author_flair": "Acolyte #65", "submission": "p8n3ev", "stickied": false, "body": "Where are the watchers?\n\nYou can also call us the lurkers, if you wish.", "is_submitter": false, "distinguished": null, "created_utc": 1629531330.0, "parent_id": "t3_p8n3ev", "replies": [{"author": "chewbaccataco", "id": "h9rl474", "score": 3, "subreddit": "TheFlyingTree", "author_flair": "Seeker #67 | Classis Veritatus", "submission": "p8n3ev", "stickied": false, "body": "The armies need *someone* to slaughter.", "is_submitter": false, "distinguished": null, "created_utc": 1629532078.0, "parent_id": "t1_h9rk8sn", "replies": [{"author": "Stand_kicker", "id": "h9rlsnp", "score": 2, "subreddit": "TheFlyingTree", "author_flair": "Acolyte #65", "submission": "p8n3ev", "stickied": false, "body": "I nominate the dolphins.", "is_submitter": false, "distinguished": null, "created_utc": 1629532667.0, "parent_id": "t1_h9rl474", "replies": [{"author": "Hjemi", "id": "h9sk8rp", "score": 2, "subreddit": "TheFlyingTree", "author_flair": "Seeker #203 | Consortii Concordus", "submission": "p8n3ev", "stickied": false, "body": "*This will be remembered in the time of the cleansing...*", "is_submitter": false, "distinguished": null, "created_utc": 1629556645.0, "parent_id": "t1_h9rlsnp", "replies": [{"author": "Stand_kicker", "id": "h9stvih", "score": 2, "subreddit": "TheFlyingTree", "author_flair": "Acolyte #65", "submission": "p8n3ev", "stickied": false, "body": "Didn't know I was in a game made by Telltale.", "is_submitter": false, "distinguished": null, "created_utc": 1629561079.0, "parent_id": "t1_h9sk8rp", "replies": []}]}]}]}]}, {"author": "Zabawa13", "id": "h9rp8ly", "score": 4, "subreddit": "TheFlyingTree", "author_flair": "Seeker #229 | Classis Veritatus", "submission": "p8n3ev", "stickied": false, "body": "It must have taken quite some time to organise this stuff", "is_submitter": false, "distinguished": null, "created_utc": 1629535708.0, "parent_id": "t3_p8n3ev", "replies": []}, {"author": "Kelyaan", "id": "h9s9628", "score": 5, "subreddit": "TheFlyingTree", "author_flair": "Seeker #271 | Consortii Concordus", "submission": "p8n3ev", "stickied": false, "body": "69ing dolphins let's go.", "is_submitter": false, "distinguished": null, "created_utc": 1629550973.0, "parent_id": "t3_p8n3ev", "replies": []}, {"author": "JavaElemental", "id": "h9vam9m", "score": 5, "subreddit": "TheFlyingTree", "author_flair": "Seeker #62", "submission": "p8n3ev", "stickied": false, "body": "I guess I'll just found my own fifth house. Obliviates, perhaps.", "is_submitter": false, "distinguished": null, "created_utc": 1629603232.0, "parent_id": "t3_p8n3ev", "replies": []}, {"author": "chewbaccataco", "id": "h9rjs3o", "score": 3, "subreddit": "TheFlyingTree", "author_flair": "Seeker #67 | Classis Veritatus", "submission": "p8n3ev", "stickied": false, "body": "Dog Pound up in here!", "is_submitter": false, "distinguished": null, "created_utc": 1629530943.0, "parent_id": "t3_p8n3ev", "replies": [{"author": "DELETED", "id": "h9unysz", "score": 1, "subreddit": "TheFlyingTree", "author_flair": null, "submission": "p8n3ev", "stickied": false, "body": "Woof Woof!", "is_submitter": false, "distinguished": null, "created_utc": 1629591907.0, "parent_id": "t1_h9rjs3o", "replies": []}]}, {"author": "bmichell21", "id": "h9rn5h6", "score": 3, "subreddit": "TheFlyingTree", "author_flair": "Seeker #8", "submission": "p8n3ev", "stickied": false, "body": "And with thunderous applause we welcome death into our life, so that alas yet our appetites be sated.", "is_submitter": false, "distinguished": null, "created_utc": 1629533853.0, "parent_id": "t3_p8n3ev", "replies": []}, {"author": "Meshuggah333", "id": "h9rzrzb", "score": 3, "subreddit": "TheFlyingTree", "author_flair": "Acolyte #95", "submission": "p8n3ev", "stickied": false, "body": "So there are factions now, I totally missed that lol.", "is_submitter": false, "distinguished": null, "created_utc": 1629544820.0, "parent_id": "t3_p8n3ev", "replies": []}, {"author": "Ice_Nade", "id": "h9t2hu8", "score": 3, "subreddit": "TheFlyingTree", "author_flair": "Acolyte #123", "submission": "p8n3ev", "stickied": false, "body": "anyone wanna place bets on how this will go?", "is_submitter": false, "distinguished": null, "created_utc": 1629564938.0, "parent_id": "t3_p8n3ev", "replies": [{"author": "notdeepee", "id": "h9uvkf9", "score": 2, "subreddit": "TheFlyingTree", "author_flair": "Acolyte #80 | Legio Virtus", "submission": "p8n3ev", "stickied": false, "body": "Bread eating contest. Of course!", "is_submitter": false, "distinguished": null, "created_utc": 1629595673.0, "parent_id": "t1_h9t2hu8", "replies": [{"author": "Ice_Nade", "id": "h9vytkf", "score": 2, "subreddit": "TheFlyingTree", "author_flair": "Acolyte #123", "submission": "p8n3ev", "stickied": false, "body": "Bruh moment", "is_submitter": false, "distinguished": null, "created_utc": 1629619735.0, "parent_id": "t1_h9uvkf9", "replies": []}, {"author": "vook485", "id": "h9vtlzb", "score": 1, "subreddit": "TheFlyingTree", "author_flair": "Seeker #113", "submission": "p8n3ev", "stickied": false, "body": "Followed by cracker challenge, cinnamon challenge, chilli powder challenge, Cayenne powder challenge, \u2026, capsaicin challenge, and finally resiniferatoxin challenge. Winner gets to solo the death by cocoa challenge (sugar and other ingredients in \"chocolate\" candies optional), which requires consuming in 1 hour enough cocoa that the cumulative caffeine content exceeds that of a 12-pack of energy drinks.", "is_submitter": false, "distinguished": null, "created_utc": 1629615448.0, "parent_id": "t1_h9uvkf9", "replies": [{"author": "gr13fy", "id": "h9xno3d", "score": 2, "subreddit": "TheFlyingTree", "author_flair": "Seeker #223", "submission": "p8n3ev", "stickied": false, "body": "it turns out we're just hungry.", "is_submitter": false, "distinguished": null, "created_utc": 1629654915.0, "parent_id": "t1_h9vtlzb", "replies": []}]}]}]}, {"author": "pine_ary", "id": "h9s4d4e", "score": 2, "subreddit": "TheFlyingTree", "author_flair": "Seeker #74", "submission": "p8n3ev", "stickied": false, "body": "What? I replied to the thread but I\u2018m not in any group?", "is_submitter": false, "distinguished": null, "created_utc": 1629548068.0, "parent_id": "t3_p8n3ev", "replies": [{"author": "Admarie25", "id": "h9s4har", "score": 2, "subreddit": "TheFlyingTree", "author_flair": "Acolyte #162", "submission": "p8n3ev", "stickied": false, "body": "Same!", "is_submitter": false, "distinguished": null, "created_utc": 1629548143.0, "parent_id": "t1_h9s4d4e", "replies": [{"author": "clovepod", "id": "h9shbnr", "score": 6, "subreddit": "TheFlyingTree", "author_flair": "Seeker #83 | Consortii Concordus", "submission": "p8n3ev", "stickied": false, "body": "You had to fill out the Google form.", "is_submitter": false, "distinguished": null, "created_utc": 1629555253.0, "parent_id": "t1_h9s4har", "replies": [{"author": "Admarie25", "id": "h9sirvd", "score": 2, "subreddit": "TheFlyingTree", "author_flair": "Acolyte #162", "submission": "p8n3ev", "stickied": false, "body": "Thanks. Totally missed that.", "is_submitter": false, "distinguished": null, "created_utc": 1629555946.0, "parent_id": "t1_h9shbnr", "replies": [{"author": "Pwngulator", "id": "h9x7gqz", "score": 1, "subreddit": "TheFlyingTree", "author_flair": "Seeker #171", "submission": "p8n3ev", "stickied": false, "body": "Womp, same", "is_submitter": false, "distinguished": null, "created_utc": 1629648029.0, "parent_id": "t1_h9sirvd", "replies": []}]}, {"author": "Savome", "id": "h9u5sei", "score": 1, "subreddit": "TheFlyingTree", "author_flair": "Seeker #115", "submission": "p8n3ev", "stickied": false, "body": "Ah damn", "is_submitter": false, "distinguished": null, "created_utc": 1629582986.0, "parent_id": "t1_h9shbnr", "replies": [{"author": "clovepod", "id": "h9u6xpn", "score": 2, "subreddit": "TheFlyingTree", "author_flair": "Seeker #83 | Consortii Concordus", "submission": "p8n3ev", "stickied": false, "body": "I don\u2019t think this will be the only opportunity, based on a comment by Archon.", "is_submitter": false, "distinguished": null, "created_utc": 1629583530.0, "parent_id": "t1_h9u5sei", "replies": [{"author": "Savome", "id": "h9u8bhf", "score": 3, "subreddit": "TheFlyingTree", "author_flair": "Seeker #115", "submission": "p8n3ev", "stickied": false, "body": "That's good! Really hoping to become a 69 dolphin someday", "is_submitter": false, "distinguished": null, "created_utc": 1629584194.0, "parent_id": "t1_h9u6xpn", "replies": [{"author": "chewbaccataco", "id": "h9utg78", "score": 2, "subreddit": "TheFlyingTree", "author_flair": "Seeker #67 | Classis Veritatus", "submission": "p8n3ev", "stickied": false, "body": "Good to have life goals", "is_submitter": false, "distinguished": null, "created_utc": 1629594625.0, "parent_id": "t1_h9u8bhf", "replies": []}]}]}]}]}]}, {"author": "campaigner1147", "id": "h9t72g2", "score": 2, "subreddit": "TheFlyingTree", "author_flair": "Acolyte #115", "submission": "p8n3ev", "stickied": false, "body": "Same! I never saw a Google form. Dang it. I think another group should be added for the procrastinators and people who missed that. Lol", "is_submitter": false, "distinguished": null, "created_utc": 1629566995.0, "parent_id": "t1_h9s4d4e", "replies": []}, {"author": "FalconRelevant", "id": "h9t99g5", "score": 0, "subreddit": "TheFlyingTree", "author_flair": "Archon", "submission": "p8n3ev", "stickied": false, "body": "There was a form you had to fill.", "is_submitter": true, "distinguished": null, "created_utc": 1629567983.0, "parent_id": "t1_h9s4d4e", "replies": [{"author": "pine_ary", "id": "h9t9fs1", "score": 1, "subreddit": "TheFlyingTree", "author_flair": "Seeker #74", "submission": "p8n3ev", "stickied": false, "body": "Well shucks. So if I\u2018m not in any of these things I can\u2018t advance ranks anymore? This whole thing is a hot mess. And how will this work for new members?", "is_submitter": false, "distinguished": null, "created_utc": 1629568062.0, "parent_id": "t1_h9t99g5", "replies": [{"author": "FalconRelevant", "id": "h9ta3v7", "score": 1, "subreddit": "TheFlyingTree", "author_flair": "Archon", "submission": "p8n3ev", "stickied": false, "body": "No relation to ranks advancing for now. More people will be added to factions later.", "is_submitter": true, "distinguished": null, "created_utc": 1629568358.0, "parent_id": "t1_h9t9fs1", "replies": []}]}, {"author": "RiderHood", "id": "h9tvqbf", "score": 1, "subreddit": "TheFlyingTree", "author_flair": "Seeker #5", "submission": "p8n3ev", "stickied": false, "body": "Will we have a chance to join a faction later if we didn\u2019t make it into this round?", "is_submitter": false, "distinguished": null, "created_utc": 1629578313.0, "parent_id": "t1_h9t99g5", "replies": [{"author": "FalconRelevant", "id": "h9vluvd", "score": 1, "subreddit": "TheFlyingTree", "author_flair": "Archon", "submission": "p8n3ev", "stickied": false, "body": "Yes.", "is_submitter": true, "distinguished": null, "created_utc": 1629609820.0, "parent_id": "t1_h9tvqbf", "replies": [{"author": "TheProfNolan", "id": "h9yofa5", "score": 1, "subreddit": "TheFlyingTree", "author_flair": "Acolyte #50", "submission": "p8n3ev", "stickied": false, "body": "Will every sorting involve a Google form, or will there be other methods in the future?", "is_submitter": false, "distinguished": null, "created_utc": 1629671211.0, "parent_id": "t1_h9vluvd", "replies": []}]}]}]}]}, {"author": "synysterlemming", "id": "h9tb141", "score": 2, "subreddit": "TheFlyingTree", "author_flair": "Seeker #138", "submission": "p8n3ev", "stickied": false, "body": "So when is the Battle Royale?", "is_submitter": false, "distinguished": null, "created_utc": 1629568770.0, "parent_id": "t3_p8n3ev", "replies": [{"author": "notdeepee", "id": "h9uvhra", "score": 1, "subreddit": "TheFlyingTree", "author_flair": "Acolyte #80 | Legio Virtus", "submission": "p8n3ev", "stickied": false, "body": "\"Where we dropping bois?\"", "is_submitter": false, "distinguished": null, "created_utc": 1629595638.0, "parent_id": "t1_h9tb141", "replies": []}]}, {"author": "boringlesbian", "id": "h9tgtqc", "score": 2, "subreddit": "TheFlyingTree", "author_flair": "Seeker #261 | Consortii Concordus", "submission": "p8n3ev", "stickied": false, "body": "We will bring balance to the universe.", "is_submitter": false, "distinguished": null, "created_utc": 1629571402.0, "parent_id": "t3_p8n3ev", "replies": []}, {"author": "weeb2000", "id": "h9ukb88", "score": 2, "subreddit": "TheFlyingTree", "author_flair": "Seeker #121 | Legio Virtus", "submission": "p8n3ev", "stickied": false, "body": "dang. i was hoping for the cool bird one", "is_submitter": false, "distinguished": null, "created_utc": 1629590086.0, "parent_id": "t3_p8n3ev", "replies": []}, {"author": "WikiContributor83", "id": "h9un1sz", "score": 2, "subreddit": "TheFlyingTree", "author_flair": "Acolyte #120", "submission": "p8n3ev", "stickied": false, "body": "Like others here I didn\u2019t see anything about a Google Form.", "is_submitter": false, "distinguished": null, "created_utc": 1629591451.0, "parent_id": "t3_p8n3ev", "replies": [{"author": "chewbaccataco", "id": "h9uty3z", "score": 3, "subreddit": "TheFlyingTree", "author_flair": "Seeker #67 | Classis Veritatus", "submission": "p8n3ev", "stickied": false, "body": "Your first test did not go so well.", "is_submitter": false, "distinguished": null, "created_utc": 1629594879.0, "parent_id": "t1_h9un1sz", "replies": []}]}, {"author": "U_L_Uus", "id": "h9y01bu", "score": 2, "subreddit": "TheFlyingTree", "author_flair": "Acolyte #119 | Classis Veritatus", "submission": "p8n3ev", "stickied": false, "body": "I kinda somehow expected to be put into the new team were it to be created. Just as planned", "is_submitter": false, "distinguished": null, "created_utc": 1629660282.0, "parent_id": "t3_p8n3ev", "replies": []}, {"author": "stachldrat", "id": "h9ytkyu", "score": 2, "subreddit": "TheFlyingTree", "author_flair": "Seeker #251 | Ordo Cognitus", "submission": "p8n3ev", "stickied": false, "body": "I'm still not clear on what we're supposed to be doing with this now", "is_submitter": false, "distinguished": null, "created_utc": 1629673669.0, "parent_id": "t3_p8n3ev", "replies": []}, {"author": "Fact_Mysterious", "id": "h9zkufx", "score": 2, "subreddit": "TheFlyingTree", "author_flair": "Seeker #31", "submission": "p8n3ev", "stickied": false, "body": "I think I spelled my username wrong ib the google form", "is_submitter": false, "distinguished": null, "created_utc": 1629687165.0, "parent_id": "t3_p8n3ev", "replies": []}, {"author": "ToastyCaribiu84", "id": "h9rtwt8", "score": 1, "subreddit": "TheFlyingTree", "author_flair": "Acolyte #42", "submission": "p8n3ev", "stickied": false, "body": "Hell yeah, I got lucky", "is_submitter": false, "distinguished": null, "created_utc": 1629539874.0, "parent_id": "t3_p8n3ev", "replies": []}, {"author": "Riadys", "id": "h9ruwh5", "score": 1, "subreddit": "TheFlyingTree", "author_flair": "Seeker #151 | Consortii Concordus", "submission": "p8n3ev", "stickied": false, "body": "So is not everyone going to be sorted into a faction? I assumed we all would regardless; I mainly filled in the form to give my opinion on the whole war thing and how it should work.\n\nOn that note, u/FalconRelevant did you make a decision on if and how this will tie into the ranks?", "is_submitter": false, "distinguished": null, "created_utc": 1629540751.0, "parent_id": "t3_p8n3ev", "replies": [{"author": "FalconRelevant", "id": "h9ruzrr", "score": 2, "subreddit": "TheFlyingTree", "author_flair": "Archon", "submission": "p8n3ev", "stickied": false, "body": "For now it will not affect the ranks. More people will be added to the factions later.", "is_submitter": true, "distinguished": null, "created_utc": 1629540833.0, "parent_id": "t1_h9ruwh5", "replies": [{"author": "Riadys", "id": "h9rv41t", "score": 2, "subreddit": "TheFlyingTree", "author_flair": "Seeker #151 | Consortii Concordus", "submission": "p8n3ev", "stickied": false, "body": "Got it. Cheers.", "is_submitter": false, "distinguished": null, "created_utc": 1629540940.0, "parent_id": "t1_h9ruzrr", "replies": []}]}]}, {"author": "BaddDadd2010", "id": "h9s119h", "score": 1, "subreddit": "TheFlyingTree", "author_flair": "Seeker #50", "submission": "p8n3ev", "stickied": false, "body": "I thought this could be fun, and attempted to register, but I couldn't answer one of the questions without lying.  So I guess I'm not allowed to participate.", "is_submitter": false, "distinguished": null, "created_utc": 1629545782.0, "parent_id": "t3_p8n3ev", "replies": [{"author": "bethcano", "id": "h9sfdxp", "score": 1, "subreddit": "TheFlyingTree", "author_flair": "Seeker #40", "submission": "p8n3ev", "stickied": false, "body": "Which question, out of curiosity?", "is_submitter": false, "distinguished": null, "created_utc": 1629554283.0, "parent_id": "t1_h9s119h", "replies": [{"author": "BaddDadd2010", "id": "h9sfyn6", "score": 5, "subreddit": "TheFlyingTree", "author_flair": "Seeker #50", "submission": "p8n3ev", "stickied": false, "body": "The one where you had to choose between killing your loved one, yourself, or 25,000 random people.  They don't reflect reality, so there is no honest answer.\n\nThere may have been others farther down, I stopped trying when I couldn't answer that one.", "is_submitter": false, "distinguished": null, "created_utc": 1629554576.0, "parent_id": "t1_h9sfdxp", "replies": [{"author": "bethcano", "id": "h9sgclf", "score": 2, "subreddit": "TheFlyingTree", "author_flair": "Seeker #40", "submission": "p8n3ev", "stickied": false, "body": "That's fair. I understand not wanting to answer hypothetical questions. I found that one strange too.", "is_submitter": false, "distinguished": null, "created_utc": 1629554772.0, "parent_id": "t1_h9sfyn6", "replies": []}, {"author": "Walking_the_Cascades", "id": "h9t8ixe", "score": 1, "subreddit": "TheFlyingTree", "author_flair": "Seeker #68", "submission": "p8n3ev", "stickied": false, "body": "Wow! I didn't fill out the form, but if I had I would not have answered that type of question either. It's my opinion that people who come up with those types of hypothetical questions lack maturity (or at the very least, imagination), but that's another topic entirely.", "is_submitter": false, "distinguished": null, "created_utc": 1629567651.0, "parent_id": "t1_h9sfyn6", "replies": []}, {"author": "chocol8cek", "id": "h9vwlog", "score": 1, "subreddit": "TheFlyingTree", "author_flair": "Seeker #107 | Legio Virtus", "submission": "p8n3ev", "stickied": false, "body": "Oh shit, I think I accidentally answered this question wrong.\n\nI thought they were asking who will you save and I clicked on loved one.\n\nNo wonder I got sorted to Legio Virtus.", "is_submitter": false, "distinguished": null, "created_utc": 1629617873.0, "parent_id": "t1_h9sfyn6", "replies": []}]}]}, {"author": "BrynneRaine", "id": "h9sqepp", "score": 1, "subreddit": "TheFlyingTree", "author_flair": "Druid #13", "submission": "p8n3ev", "stickied": false, "body": "I didn\u2019t see questions.  Must be why I was not sorted.", "is_submitter": false, "distinguished": null, "created_utc": 1629559517.0, "parent_id": "t1_h9s119h", "replies": []}]}, {"author": "IamTJcon", "id": "h9s29m5", "score": 1, "subreddit": "TheFlyingTree", "author_flair": "Druid #10 | Ordo Cognitus", "submission": "p8n3ev", "stickied": false, "body": "Damn I got. Ordos Cognitvs \n Cool\n So when are the Hunger Games are being initiated.", "is_submitter": false, "distinguished": null, "created_utc": 1629546672.0, "parent_id": "t3_p8n3ev", "replies": [{"author": "IamTJcon", "id": "h9s2fe7", "score": 2, "subreddit": "TheFlyingTree", "author_flair": "Druid #10 | Ordo Cognitus", "submission": "p8n3ev", "stickied": false, "body": "u/FalconRelevant looks like my tags not in line.", "is_submitter": false, "distinguished": null, "created_utc": 1629546784.0, "parent_id": "t1_h9s29m5", "replies": [{"author": "FalconRelevant", "id": "h9t9nal", "score": 2, "subreddit": "TheFlyingTree", "author_flair": "Archon", "submission": "p8n3ev", "stickied": false, "body": "Oops. Lemme fix the script and run it again.", "is_submitter": true, "distinguished": null, "created_utc": 1629568154.0, "parent_id": "t1_h9s2fe7", "replies": []}]}]}, {"author": "arokace", "id": "h9sa7il", "score": 1, "subreddit": "TheFlyingTree", "author_flair": "Seeker #48", "submission": "p8n3ev", "stickied": false, "body": "How do you get sorted?  I personally can't decide.  The only one I feel for sure I wouldn't land in is Legio Virtvs.  I those traits but a lot of the other traits in other ones are waaaaay stronger.  I value knowledge/intelligence, curiousity, acceptance, harmony, equality, honesty, patience all pretty high...\n\nLegio Virtvs.  Valour, unknown, haven't been in a whole lot of situations in my life were that would come up.  Courage, wouldn't say I value it in any direction but I certainly have a decent amount of courage.  Honour I would probably value pretty high.  Sacrifice, eh.\n\nI guess since I labeled 3 from Consortia Concordvs I'd be that one but I value fraternity pretty fucking low.\n\nOrdo Cognitvs.  Primacy means something dominate right, so that would go completely against me valuing equality.  And pride I sort of take pride in, not necassarily everything but certainly has some value to me.\n\nClassis Veritatvs.  I definitely have some value in loyalty.  But duty is just kind of middle of the road.  Probably have some value in it since its sort of similar to pride.  \n\n\nP.S. glad to see we really are evolving into a cult.", "is_submitter": false, "distinguished": null, "created_utc": 1629551549.0, "parent_id": "t3_p8n3ev", "replies": []}, {"author": "SybariteAussie", "id": "h9sflqy", "score": 1, "subreddit": "TheFlyingTree", "author_flair": "Acolyte #177", "submission": "p8n3ev", "stickied": false, "body": "Hmm, either I am on the bench or about to be culled", "is_submitter": false, "distinguished": null, "created_utc": 1629554393.0, "parent_id": "t3_p8n3ev", "replies": []}, {"author": "prajnadhyana", "id": "h9sipsi", "score": 1, "subreddit": "TheFlyingTree", "author_flair": "Seeker #168", "submission": "p8n3ev", "stickied": false, "body": "Ok. Now what?", "is_submitter": false, "distinguished": null, "created_utc": 1629555919.0, "parent_id": "t3_p8n3ev", "replies": []}, {"author": "kindasortasalty", "id": "h9spjm5", "score": 1, "subreddit": "TheFlyingTree", "author_flair": "Seeker #33", "submission": "p8n3ev", "stickied": false, "body": "How does one get sorted?", "is_submitter": false, "distinguished": null, "created_utc": 1629559119.0, "parent_id": "t3_p8n3ev", "replies": [{"author": "CielTheEarl", "id": "h9vzhdv", "score": 2, "subreddit": "TheFlyingTree", "author_flair": "Seeker #172 | Consortii Concordus", "submission": "p8n3ev", "stickied": false, "body": "There's a google form for that", "is_submitter": false, "distinguished": null, "created_utc": 1629620303.0, "parent_id": "t1_h9spjm5", "replies": [{"author": "kindasortasalty", "id": "h9wj7sk", "score": 1, "subreddit": "TheFlyingTree", "author_flair": "Seeker #33", "submission": "p8n3ev", "stickied": false, "body": "Thanks", "is_submitter": false, "distinguished": null, "created_utc": 1629636253.0, "parent_id": "t1_h9vzhdv", "replies": []}]}]}, {"author": "Zealousideal_Mix_629", "id": "h9stt8w", "score": 1, "subreddit": "TheFlyingTree", "author_flair": "Acolyte #13 | Legio Virtus", "submission": "p8n3ev", "stickied": false, "body": "Go team Red Cougars (I refuse to write out that Latin nonsense)", "is_submitter": false, "distinguished": null, "created_utc": 1629561051.0, "parent_id": "t3_p8n3ev", "replies": []}, {"author": "raedr7n", "id": "h9t0jdy", "score": 1, "subreddit": "TheFlyingTree", "author_flair": "Seeker #49 | Legio Virtus", "submission": "p8n3ev", "stickied": false, "body": "So only a few people get sorted of those who did the form?", "is_submitter": false, "distinguished": null, "created_utc": 1629564072.0, "parent_id": "t3_p8n3ev", "replies": [{"author": "FalconRelevant", "id": "h9t8y2z", "score": 1, "subreddit": "TheFlyingTree", "author_flair": "Archon", "submission": "p8n3ev", "stickied": false, "body": "No, almost everyone who filled it got sorted.", "is_submitter": true, "distinguished": null, "created_utc": 1629567841.0, "parent_id": "t1_h9t0jdy", "replies": [{"author": "raedr7n", "id": "h9tbcf3", "score": 2, "subreddit": "TheFlyingTree", "author_flair": "Seeker #49 | Legio Virtus", "submission": "p8n3ev", "stickied": false, "body": "Oh, nvm. I misread it. Cool, Legio Virtvs!", "is_submitter": false, "distinguished": null, "created_utc": 1629568909.0, "parent_id": "t1_h9t8y2z", "replies": []}]}]}, {"author": "Prior_Technology_868", "id": "h9tdbve", "score": 1, "subreddit": "TheFlyingTree", "author_flair": "Acolyte #141", "submission": "p8n3ev", "stickied": false, "body": "What the dogshit. I want to be legio virtus.", "is_submitter": false, "distinguished": null, "created_utc": 1629569802.0, "parent_id": "t3_p8n3ev", "replies": []}, {"author": "adadagabaCZ", "id": "h9tq5ep", "score": 1, "subreddit": "TheFlyingTree", "author_flair": "Acolyte #12", "submission": "p8n3ev", "stickied": false, "body": "Yeeeeee i missed out on this event lol. Too much irl work to care, I'll just post comment once a week and see how the things turn out", "is_submitter": false, "distinguished": null, "created_utc": 1629575734.0, "parent_id": "t3_p8n3ev", "replies": []}, {"author": "FreeBiskit", "id": "h9u9a8s", "score": 1, "subreddit": "TheFlyingTree", "author_flair": "Seeker #174", "submission": "p8n3ev", "stickied": false, "body": "When did this happen?", "is_submitter": false, "distinguished": null, "created_utc": 1629584654.0, "parent_id": "t3_p8n3ev", "replies": []}, {"author": "notdeepee", "id": "h9uw2bo", "score": 1, "subreddit": "TheFlyingTree", "author_flair": "Acolyte #80 | Legio Virtus", "submission": "p8n3ev", "stickied": false, "body": "\"rawr! oh noes did I scawe uwu!?\"", "is_submitter": false, "distinguished": null, "created_utc": 1629595914.0, "parent_id": "t3_p8n3ev", "replies": []}, {"author": "chocol8cek", "id": "h9vvspw", "score": 1, "subreddit": "TheFlyingTree", "author_flair": "Seeker #107 | Legio Virtus", "submission": "p8n3ev", "stickied": false, "body": "Aww Legio was the last thing I wanted to be sorted into. ):\n\nIs it common for people to get sorted into factions that weren't in their choice? I remember picking the other two as my two options.", "is_submitter": false, "distinguished": null, "created_utc": 1629617202.0, "parent_id": "t3_p8n3ev", "replies": []}, {"author": "Mr--Elephant", "id": "h9x2j6a", "score": 1, "subreddit": "TheFlyingTree", "author_flair": "Acolyte #72 | Ordo Cognitus", "submission": "p8n3ev", "stickied": false, "body": "ALRIGHT YEAH, I GOT BIRB FACTION", "is_submitter": false, "distinguished": null, "created_utc": 1629645874.0, "parent_id": "t3_p8n3ev", "replies": []}, {"author": "SaxAppeal", "id": "h9xv4ng", "score": 1, "subreddit": "TheFlyingTree", "author_flair": "Acolyte #171", "submission": "p8n3ev", "stickied": false, "body": "How does one achieve this sorting which is set forth herein", "is_submitter": false, "distinguished": null, "created_utc": 1629658151.0, "parent_id": "t3_p8n3ev", "replies": []}, {"author": "ravenclaw1138", "id": "hai25zf", "score": 1, "subreddit": "TheFlyingTree", "author_flair": "Seeker #27 | Classis Veritatus", "submission": "p8n3ev", "stickied": false, "body": "Interesting, I was sorted into neither of my top picks.", "is_submitter": false, "distinguished": null, "created_utc": 1630028033.0, "parent_id": "t3_p8n3ev", "replies": []}, {"author": "Shouia", "id": "hapvihi", "score": 1, "subreddit": "TheFlyingTree", "author_flair": "", "submission": "p8n3ev", "stickied": false, "body": "Ha. People really hated the horse.", "is_submitter": false, "distinguished": null, "created_utc": 1630179345.0, "parent_id": "t3_p8n3ev", "replies": []}]}