{"title": "Christmas in August and a cool molded dragon mug! Photos, Week 11.", "name": "t3_ozlo2s", "url": "https://www.reddit.com/gallery/ozlo2s", "selftext": "", "score": 3, "upvote_ratio": 0.8, "permalink": "/r/TheFlyingTree/comments/ozlo2s/christmas_in_august_and_a_cool_molded_dragon_mug/", "id": "ozlo2s", "author": "TatianaAlena", "link_flair_text": "Fascinating", "num_comments": 0, "over_18": false, "spoiler": false, "pinned": false, "locked": false, "distinguished": null, "created_utc": 1628306460.0, "comments": []}